regrez/__init__.py
regrez/main.py
regrez-2.1.8.dist-info/METADATA
regrez-2.1.8.dist-info/WHEEL
regrez-2.1.8.dist-info/top_level.txt
regrez-2.1.8.dist-info/RECORD
