Metadata-Version: 2.1
Name: regrez
Version: 2.1.8
Summary: Easiest way to implement linear regression.
Home-page: UNKNOWN
Author: Mehmet Utku OZTURK
Author-email: <contact@ælphard.tk>
License: UNKNOWN
Keywords: regression,machine learning
Platform: UNKNOWN
Classifier: Development Status :: 3 - Alpha
Classifier: Intended Audience :: Developers
Classifier: Natural Language :: English
Classifier: Programming Language :: Python :: 3
Requires-Dist: matplotlib
Requires-Dist: sklearn
Requires-Dist: numpy
Requires-Dist: pandas
